README.md
setup.py
lenluhub/__init__.py
lenluhub.egg-info/PKG-INFO
lenluhub.egg-info/SOURCES.txt
lenluhub.egg-info/dependency_links.txt
lenluhub.egg-info/requires.txt
lenluhub.egg-info/top_level.txt
lenluhub/common/__init__.py
lenluhub/common/errors.py
lenluhub/common/utils.py
lenluhub/dataset/__init__.py
lenluhub/dataset/classification_dataset.py
lenluhub/dataset/dataset_utils.py
lenluhub/dataset/sequence_label_dataset.py
lenluhub/evaluate/__init__.py
lenluhub/evaluate/metrics.py
lenluhub/processor/__init__.py
lenluhub/processor/tokenizer.py
lenluhub/tasks/__init__.py
lenluhub/tasks/classification_task.py
lenluhub/tasks/joint_task.py
lenluhub/tasks/sequence_label_task.py
lenluhub/web/__init__.py
lenluhub/web/handlers.py
lenluhub/web/server.py
lenluhub/web/service.py